robotframework_qtexpert/__init__.py
robotframework_qtexpert/agent.py
robotframework_qtexpert/qt_compat.py
robotframework_qtexpert/backends/__init__.py
robotframework_qtexpert/backends/a11y_linux.py
robotframework_qtexpert/backends/a11y_macos.py
robotframework_qtexpert/backends/a11y_win.py
robotframework_qtexpert/backends/agent_client.py
robotframework_qtexpert/backends/base.py
robotframework_qtexpert/keywords/__init__.py
robotframework_qtexpert/keywords/_keyword_base.py
robotframework_qtexpert/keywords/application.py
robotframework_qtexpert/keywords/generic.py
robotframework_qtexpert-0.1.2.dist-info/licenses/LICENSE
robotframework_qtexpert-0.1.2.dist-info/METADATA
robotframework_qtexpert-0.1.2.dist-info/WHEEL
robotframework_qtexpert-0.1.2.dist-info/top_level.txt
robotframework_qtexpert-0.1.2.dist-info/RECORD
