Metadata-Version: 2.4
Name: robotframework-qtexpert
Version: 0.1.2
Summary: A unified Robot Framework library for testing Qt applications via Agent or Accessibility APIs.
Author-email: Thulasi Siripireddy <tulasirm6@gmail.com>
License-Expression: Apache-2.0
Project-URL: Homepage, https://github.com/tulasirm6/robotframework-qtexpert
Project-URL: Bug Tracker, https://github.com/tulasirm6/robotframework-qtexpert/issues
Keywords: robotframework-library,qt-testing,qt-automation,pyqt,pyqt5,pyqt6,pyside,pyside2,pyside6,gui-testing,ui-automation,accessibility-testing,desktop-automation,at-spi,pywinauto,pyobjc,qtexpert,acceptance-testing
Classifier: Programming Language :: Python :: 3
Classifier: Framework :: Robot Framework
Classifier: Topic :: Software Development :: Testing
Classifier: Operating System :: OS Independent
Requires-Python: >=3.8
License-File: LICENSE
Requires-Dist: robotframework
Provides-Extra: agent-pyqt5
Requires-Dist: PyQt5; extra == "agent-pyqt5"
Provides-Extra: agent-pyside2
Requires-Dist: PySide2; extra == "agent-pyside2"
Provides-Extra: agent-pyqt6
Requires-Dist: PyQt6; extra == "agent-pyqt6"
Provides-Extra: agent-pyside6
Requires-Dist: PySide6; extra == "agent-pyside6"
Provides-Extra: agent-all
Requires-Dist: PyQt5; extra == "agent-all"
Requires-Dist: PySide2; extra == "agent-all"
Requires-Dist: PyQt6; extra == "agent-all"
Requires-Dist: PySide6; extra == "agent-all"
Provides-Extra: a11y-windows
Requires-Dist: pywinauto; extra == "a11y-windows"
Provides-Extra: a11y-linux
Requires-Dist: pyatspi; extra == "a11y-linux"
Provides-Extra: a11y-macos
Requires-Dist: pyobjc-framework-Cocoa; extra == "a11y-macos"
Requires-Dist: pyobjc-framework-Quartz; extra == "a11y-macos"
Provides-Extra: a11y-all
Requires-Dist: pywinauto; extra == "a11y-all"
Requires-Dist: pyatspi; extra == "a11y-all"
Requires-Dist: pyobjc-framework-Cocoa; extra == "a11y-all"
Requires-Dist: pyobjc-framework-Quartz; extra == "a11y-all"
Provides-Extra: all
Requires-Dist: PyQt5; extra == "all"
Requires-Dist: PySide2; extra == "all"
Requires-Dist: PyQt6; extra == "all"
Requires-Dist: PySide6; extra == "all"
Requires-Dist: pywinauto; extra == "all"
Requires-Dist: pyatspi; extra == "all"
Requires-Dist: pyobjc-framework-Cocoa; extra == "all"
Requires-Dist: pyobjc-framework-Quartz; extra == "all"
Dynamic: license-file
